2BitCounter/design.v
module sequential_circuit (Q, clk, reset);
  input clk, reset;
  output [1:0] Q;

  // Register for binary counter
  reg [1:0] Flop;

  // Binary counter logic
  always @(posedge clk or posedge reset)
  begin
    if (reset == 1'b1)
      Flop <= 2'b00;
    else
      Flop <= Flop + 1'b1;
  end

  // Output assignment
  assign Q = Flop;

endmodule

2BitCounter/testbench.v
module tb();

  reg reset;
  reg clk = 0;
  wire [1:0] Q;

  sequential_circuit dut (
    .clk(clk),
    .reset(reset),
    .Q(Q)
  );

  always begin
    clk <= ~clk;
    #5;
  end

  initial begin
    reset <= 1'b1;
    #10;
    reset <= 1'b0;
    #200;
    $finish;
  end

  initial begin
    $dumpfile("dump.vcd");
    $dumpvars(0);
  end

endmodule
     
// iverilog -o out.vpp testbench.v design.v dump.vcd 
// vvp out.vpp 
// gtkware dump.vcd

2BitCounter/dump.vcd
$date
	Wed Nov 15 12:13:48 2023
$end
$version
	Icarus Verilog
$end
$timescale
	1s
$end
$scope module tb $end
$var wire 2 ! Q [1:0] $end
$var reg 1 " clk $end
$var reg 1 # reset $end
$scope module dut $end
$var wire 2 $ Q [1:0] $end
$var wire 1 " clk $end
$var wire 1 # reset $end
$var reg 2 % Flop [1:0] $end
$upscope $end
$upscope $end
$enddefinitions $end
$comment Show the parameter values. $end
$dumpall
$end
#0
$dumpvars
b0 %
b0 $
1#
1"
b0 !
$end
#5
0"
#10
b1 !
b1 $
b1 %
1"
0#
#15
0"
#20
b10 !
b10 $
b10 %
1"
#25
0"
#30
b11 !
b11 $
b11 %
1"
#35
0"
#40
b0 !
b0 $
b0 %
1"
#45
0"
#50
b1 !
b1 $
b1 %
1"
#55
0"
#60
b10 !
b10 $
b10 %
1"
#65
0"
#70
b11 !
b11 $
b11 %
1"
#75
0"
#80
b0 !
b0 $
b0 %
1"
#85
0"
#90
b1 !
b1 $
b1 %
1"
#95
0"
#100
b10 !
b10 $
b10 %
1"
#105
0"
#110
b11 !
b11 $
b11 %
1"
